score_rbs/__init__.py
score_rbs/score_rbs.py
score_rbs-0.5.dist-info/LICENSE
score_rbs-0.5.dist-info/METADATA
score_rbs-0.5.dist-info/WHEEL
score_rbs-0.5.dist-info/top_level.txt
score_rbs-0.5.dist-info/RECORD
